{"updatedAt":"2026-03-14T10:07:14.387Z","createdAt":"2026-03-07T07:46:58.093Z","id":"dO77E4A3PI9DvxVw","name":"[Util V2] Send WhatsApp","description":null,"active":true,"isArchived":false,"nodes":[{"parameters":{"inputSource":"passthrough"},"id":"uwv2-start","name":"Start","type":"n8n-nodes-base.executeWorkflowTrigger","typeVersion":1.1,"position":[240,304]},{"parameters":{"jsCode":"const d = $('Start').first().json || {};\nconst base = { messaging_product: 'whatsapp', to: String(d.chat_id || '') };\nconst userLanguage = String(d.user_language || 'en');\nconst buttons = (Array.isArray(d.buttons) ? d.buttons : []).filter((button) => button && button.id && button.title);\nconst sections = Array.isArray(d.list_sections) ? d.list_sections : [];\n\n// S7: Button title translations by language\nconst BUTTON_LABELS = {\n  en: { view_cart:'🛒 View Cart', checkout:'✓ Checkout', browse:'Shop Items', cancel:'Cancel', track_order:'Track Order', get_promos:'Offers', start_shopping:'Shop Items', add_more:'Add Items', new_order:'Shop Again', confirm_order:'Confirm Order', add_address:'Change Address', cancel_order:'Clear Cart', language_select:'🌐 Language' },\n  hi: { view_cart:'🛒 कार्ट', checkout:'✓ ऑर्डर', browse:'खरीदारी', cancel:'रद्द', track_order:'ट्रैक करें', get_promos:'ऑफर', start_shopping:'खरीदारी', add_more:'और जोड़ें', new_order:'फिर खरीदें', confirm_order:'ऑर्डर करें', add_address:'पता बदलें', cancel_order:'कार्ट साफ', language_select:'🌐 भाषा' },\n  bn: { view_cart:'🛒 কার্ট', checkout:'✓ অর্ডার', browse:'কেনাকাটা', cancel:'বাতিল', track_order:'ট্র্যাক', get_promos:'অফার', start_shopping:'কেনাকাটা', add_more:'আরো যোগ', new_order:'আবার কিনুন', confirm_order:'নিশ্চিত করুন', add_address:'ঠিকানা বদলান', cancel_order:'কার্ট খালি', language_select:'🌐 ভাষা' },\n  te: { view_cart:'🛒 కార్ట్', checkout:'✓ ఆర్డర్', browse:'షాపింగ్', cancel:'రద్దు', track_order:'ట్రాక్', get_promos:'ఆఫర్లు', start_shopping:'షాపింగ్', add_more:'మరింత', new_order:'మళ్ళీ కొనండి', confirm_order:'నిర్ధారించు', add_address:'చిరునామా', cancel_order:'కార్ట్ క్లియర్', language_select:'🌐 భాష' },\n  mr: { view_cart:'🛒 कार्ट', checkout:'✓ ऑर्डर', browse:'खरेदी', cancel:'रद्द', track_order:'ट्रॅक', get_promos:'ऑफर', start_shopping:'खरेदी', add_more:'अधिक', new_order:'पुन्हा खरेदी', confirm_order:'पुष्टी करा', add_address:'पत्ता बदला', cancel_order:'कार्ट साफ', language_select:'🌐 भाषा' },\n  ta: { view_cart:'🛒 கார்ட்', checkout:'✓ ஆர்டர்', browse:'ஷாப்பிங்', cancel:'ரத்து', track_order:'டிராக்', get_promos:'ஆஃபர்', start_shopping:'ஷாப்பிங்', add_more:'மேலும்', new_order:'மீண்டும் வாங்கு', confirm_order:'உறுதிப்படுத்து', add_address:'முகவரி', cancel_order:'கார்ட் அழி', language_select:'🌐 மொழி' },\n  gu: { view_cart:'🛒 કાર્ટ', checkout:'✓ ઓર્ડર', browse:'ખરીદી', cancel:'રદ', track_order:'ટ્રૅક', get_promos:'ઓફર', start_shopping:'ખરીદી', add_more:'વધારો', new_order:'ફરી ખરીદો', confirm_order:'પુષ્ટિ', add_address:'સરનામું', cancel_order:'કાર્ટ સાફ', language_select:'🌐 ભાષા' },\n  kn: { view_cart:'🛒 ಕಾರ್ಟ್', checkout:'✓ ಆರ್ಡರ್', browse:'ಶಾಪಿಂಗ್', cancel:'ರದ್ದು', track_order:'ಟ್ರ್ಯಾಕ್', get_promos:'ಆಫರ್', start_shopping:'ಶಾಪಿಂಗ್', add_more:'ಹೆಚ್ಚು', new_order:'ಮತ್ತೆ ಕೊಳ್ಳಿ', confirm_order:'ದೃಢಪಡಿಸಿ', add_address:'ವಿಳಾಸ', cancel_order:'ಕಾರ್ಟ್ ತೆರವು', language_select:'🌐 ಭಾಷೆ' },\n  ml: { view_cart:'🛒 കാർട്ട്', checkout:'✓ ഓർഡർ', browse:'ഷോപ്പിംഗ്', cancel:'റദ്ദാക്കൽ', track_order:'ട്രാക്ക്', get_promos:'ഓഫർ', start_shopping:'ഷോപ്പിംഗ്', add_more:'കൂടുതൽ', new_order:'വീണ്ടും', confirm_order:'സ്ഥിരീകരിക്കുക', add_address:'വിലാസം', cancel_order:'കാർട്ട് മായ്ക്കുക', language_select:'🌐 ഭാഷ' },\n  or: { view_cart:'🛒 କାର୍ଟ', checkout:'✓ ଅର୍ଡର', browse:'କେନାକାଟା', cancel:'ବାତିଲ', track_order:'ଟ୍ରାକ', get_promos:'ଅଫର', start_shopping:'କେନାକାଟା', add_more:'ଆହୁରି', new_order:'ପୁଣି କିଣ', confirm_order:'ନିଶ୍ଚିତ', add_address:'ଠିକଣା', cancel_order:'କାର୍ଟ ଖାଲି', language_select:'🌐 ଭାଷା' },\n  pa: { view_cart:'🛒 ਕਾਰਟ', checkout:'✓ ਆਰਡਰ', browse:'ਖਰੀਦਾਰੀ', cancel:'ਰੱਦ', track_order:'ਟਰੈਕ', get_promos:'ਆਫਰ', start_shopping:'ਖਰੀਦਾਰੀ', add_more:'ਹੋਰ', new_order:'ਦੁਬਾਰਾ', confirm_order:'ਪੁਸ਼ਟੀ', add_address:'ਪਤਾ', cancel_order:'ਕਾਰਟ ਸਾਫ਼', language_select:'🌐 ਭਾਸ਼ਾ' },\n};\n\n// Translate button titles\nconst translateButtons = (btns) => {\n  const labels = BUTTON_LABELS[userLanguage] || BUTTON_LABELS['en'];\n  return btns.map(btn => ({\n    id: btn.id,\n    title: labels[btn.id] || btn.title\n  }));\n};\n\nconst translatedButtons = translateButtons(buttons);\n\nlet payload;\nif (d.message_type === 'button') {\n  if (translatedButtons.length > 3) {\n    payload = {\n      ...base,\n      type: 'interactive',\n      interactive: {\n        type: 'list',\n        body: { text: String(d.body_text || '') },\n        action: {\n          button: 'Menu',\n          sections: sections.length ? sections : [{\n            title: 'Choose an option',\n            rows: translatedButtons.map((button) => ({\n              id: String(button.id || ''),\n              title: String(button.title || '').slice(0, 24),\n            })),\n          }],\n        },\n      },\n    };\n  } else {\n    payload = {\n      ...base,\n      type: 'interactive',\n      interactive: {\n        type: 'button',\n        body: { text: String(d.body_text || '') },\n        action: {\n          buttons: translatedButtons.map((button) => ({\n            type: 'reply',\n            reply: {\n              id: String(button.id || ''),\n              title: String(button.title || '').slice(0, 20),\n            },\n          })),\n        },\n      },\n    };\n  }\n} else if (d.message_type === 'list') {\n  payload = {\n    ...base,\n    type: 'interactive',\n    interactive: {\n      type: 'list',\n      body: { text: String(d.body_text || '') },\n      action: {\n        button: 'Menu',\n        sections,\n      },\n    },\n  };\n} else {\n  payload = {\n    ...base,\n    type: 'text',\n    text: { body: String(d.body_text || '') },\n  };\n}\n\nreturn [{ json: payload }];"},"id":"uwv2-build-payload","name":"Build Payload","type":"n8n-nodes-base.code","typeVersion":2,"position":[464,304]},{"parameters":{"method":"POST","url":"https://graph.facebook.com/v19.0/1012592638608632/messages","authentication":"predefinedCredentialType","nodeCredentialType":"whatsAppApi","sendHeaders":true,"headerParameters":{"parameters":[{"name":"Content-Type","value":"application/json"}]},"sendBody":true,"specifyBody":"json","jsonBody":"={{ JSON.stringify($json) }}","options":{}},"id":"uwv2-send-wa","name":"Send to WhatsApp","type":"n8n-nodes-base.httpRequest","typeVersion":4.4,"position":[688,304],"retryOnFail":true,"maxTries":3,"waitBetweenTries":2000,"credentials":{"whatsAppApi":{"id":"GFk530CPSyrOLT7F","name":"WhatsApp account"}},"onError":"continueRegularOutput"},{"parameters":{"jsCode":"const d = $('Start').first().json || {};\nconst payload = {\n  chat_id: String(d.chat_id || ''),\n  message_type: d.message_type || 'text',\n  body_text: String(d.body_text || ''),\n  buttons: Array.isArray(d.buttons) ? d.buttons : [],\n  list_sections: Array.isArray(d.list_sections) ? d.list_sections : [],\n  test_mode: d.test_mode === true,\n};\n\nreturn [{ json: payload }];"},"id":"uwv2-return-live","name":"Return Live Payload","type":"n8n-nodes-base.code","typeVersion":2,"position":[912,304]}],"connections":{"Start":{"main":[[{"node":"Build Payload","type":"main","index":0}]]},"Build Payload":{"main":[[{"node":"Send to WhatsApp","type":"main","index":0}]]},"Send to WhatsApp":{"main":[[{"node":"Return Live Payload","type":"main","index":0}]]}},"settings":{"executionOrder":"v1","callerPolicy":"workflowsFromSameOwner","availableInMCP":false},"staticData":null,"meta":null,"pinData":{},"versionId":"bf123997-b282-4ddb-853a-fa60a70c33da","activeVersionId":"bf123997-b282-4ddb-853a-fa60a70c33da","versionCounter":68,"triggerCount":0,"shared":[{"updatedAt":"2026-03-07T07:46:58.093Z","createdAt":"2026-03-07T07:46:58.093Z","role":"workflow:owner","workflowId":"dO77E4A3PI9DvxVw","projectId":"IDlW7VSwSQis1BZL","project":{"updatedAt":"2026-02-08T17:38:30.859Z","createdAt":"2026-02-08T17:36:33.972Z","id":"IDlW7VSwSQis1BZL","name":"Vishnu Pratap <vishnupratapkumar@gmail.com>","type":"personal","icon":null,"description":null,"creatorId":"26516b95-0143-4657-99c5-c7cf19c81981"}}],"tags":[],"activeVersion":{"updatedAt":"2026-03-14T10:07:14.396Z","createdAt":"2026-03-14T10:07:14.396Z","versionId":"bf123997-b282-4ddb-853a-fa60a70c33da","workflowId":"dO77E4A3PI9DvxVw","nodes":[{"parameters":{"inputSource":"passthrough"},"id":"uwv2-start","name":"Start","type":"n8n-nodes-base.executeWorkflowTrigger","typeVersion":1.1,"position":[240,304]},{"parameters":{"jsCode":"const d = $('Start').first().json || {};\nconst base = { messaging_product: 'whatsapp', to: String(d.chat_id || '') };\nconst userLanguage = String(d.user_language || 'en');\nconst buttons = (Array.isArray(d.buttons) ? d.buttons : []).filter((button) => button && button.id && button.title);\nconst sections = Array.isArray(d.list_sections) ? d.list_sections : [];\n\n// S7: Button title translations by language\nconst BUTTON_LABELS = {\n  en: { view_cart:'🛒 View Cart', checkout:'✓ Checkout', browse:'Shop Items', cancel:'Cancel', track_order:'Track Order', get_promos:'Offers', start_shopping:'Shop Items', add_more:'Add Items', new_order:'Shop Again', confirm_order:'Confirm Order', add_address:'Change Address', cancel_order:'Clear Cart', language_select:'🌐 Language' },\n  hi: { view_cart:'🛒 कार्ट', checkout:'✓ ऑर्डर', browse:'खरीदारी', cancel:'रद्द', track_order:'ट्रैक करें', get_promos:'ऑफर', start_shopping:'खरीदारी', add_more:'और जोड़ें', new_order:'फिर खरीदें', confirm_order:'ऑर्डर करें', add_address:'पता बदलें', cancel_order:'कार्ट साफ', language_select:'🌐 भाषा' },\n  bn: { view_cart:'🛒 কার্ট', checkout:'✓ অর্ডার', browse:'কেনাকাটা', cancel:'বাতিল', track_order:'ট্র্যাক', get_promos:'অফার', start_shopping:'কেনাকাটা', add_more:'আরো যোগ', new_order:'আবার কিনুন', confirm_order:'নিশ্চিত করুন', add_address:'ঠিকানা বদলান', cancel_order:'কার্ট খালি', language_select:'🌐 ভাষা' },\n  te: { view_cart:'🛒 కార్ట్', checkout:'✓ ఆర్డర్', browse:'షాపింగ్', cancel:'రద్దు', track_order:'ట్రాక్', get_promos:'ఆఫర్లు', start_shopping:'షాపింగ్', add_more:'మరింత', new_order:'మళ్ళీ కొనండి', confirm_order:'నిర్ధారించు', add_address:'చిరునామా', cancel_order:'కార్ట్ క్లియర్', language_select:'🌐 భాష' },\n  mr: { view_cart:'🛒 कार्ट', checkout:'✓ ऑर्डर', browse:'खरेदी', cancel:'रद्द', track_order:'ट्रॅक', get_promos:'ऑफर', start_shopping:'खरेदी', add_more:'अधिक', new_order:'पुन्हा खरेदी', confirm_order:'पुष्टी करा', add_address:'पत्ता बदला', cancel_order:'कार्ट साफ', language_select:'🌐 भाषा' },\n  ta: { view_cart:'🛒 கார்ட்', checkout:'✓ ஆர்டர்', browse:'ஷாப்பிங்', cancel:'ரத்து', track_order:'டிராக்', get_promos:'ஆஃபர்', start_shopping:'ஷாப்பிங்', add_more:'மேலும்', new_order:'மீண்டும் வாங்கு', confirm_order:'உறுதிப்படுத்து', add_address:'முகவரி', cancel_order:'கார்ட் அழி', language_select:'🌐 மொழி' },\n  gu: { view_cart:'🛒 કાર્ટ', checkout:'✓ ઓર્ડર', browse:'ખરીદી', cancel:'રદ', track_order:'ટ્રૅક', get_promos:'ઓફર', start_shopping:'ખરીદી', add_more:'વધારો', new_order:'ફરી ખરીદો', confirm_order:'પુષ્ટિ', add_address:'સરનામું', cancel_order:'કાર્ટ સાફ', language_select:'🌐 ભાષા' },\n  kn: { view_cart:'🛒 ಕಾರ್ಟ್', checkout:'✓ ಆರ್ಡರ್', browse:'ಶಾಪಿಂಗ್', cancel:'ರದ್ದು', track_order:'ಟ್ರ್ಯಾಕ್', get_promos:'ಆಫರ್', start_shopping:'ಶಾಪಿಂಗ್', add_more:'ಹೆಚ್ಚು', new_order:'ಮತ್ತೆ ಕೊಳ್ಳಿ', confirm_order:'ದೃಢಪಡಿಸಿ', add_address:'ವಿಳಾಸ', cancel_order:'ಕಾರ್ಟ್ ತೆರವು', language_select:'🌐 ಭಾಷೆ' },\n  ml: { view_cart:'🛒 കാർട്ട്', checkout:'✓ ഓർഡർ', browse:'ഷോപ്പിംഗ്', cancel:'റദ്ദാക്കൽ', track_order:'ട്രാക്ക്', get_promos:'ഓഫർ', start_shopping:'ഷോപ്പിംഗ്', add_more:'കൂടുതൽ', new_order:'വീണ്ടും', confirm_order:'സ്ഥിരീകരിക്കുക', add_address:'വിലാസം', cancel_order:'കാർട്ട് മായ്ക്കുക', language_select:'🌐 ഭാഷ' },\n  or: { view_cart:'🛒 କାର୍ଟ', checkout:'✓ ଅର୍ଡର', browse:'କେନାକାଟା', cancel:'ବାତିଲ', track_order:'ଟ୍ରାକ', get_promos:'ଅଫର', start_shopping:'କେନାକାଟା', add_more:'ଆହୁରି', new_order:'ପୁଣି କିଣ', confirm_order:'ନିଶ୍ଚିତ', add_address:'ଠିକଣା', cancel_order:'କାର୍ଟ ଖାଲି', language_select:'🌐 ଭାଷା' },\n  pa: { view_cart:'🛒 ਕਾਰਟ', checkout:'✓ ਆਰਡਰ', browse:'ਖਰੀਦਾਰੀ', cancel:'ਰੱਦ', track_order:'ਟਰੈਕ', get_promos:'ਆਫਰ', start_shopping:'ਖਰੀਦਾਰੀ', add_more:'ਹੋਰ', new_order:'ਦੁਬਾਰਾ', confirm_order:'ਪੁਸ਼ਟੀ', add_address:'ਪਤਾ', cancel_order:'ਕਾਰਟ ਸਾਫ਼', language_select:'🌐 ਭਾਸ਼ਾ' },\n};\n\n// Translate button titles\nconst translateButtons = (btns) => {\n  const labels = BUTTON_LABELS[userLanguage] || BUTTON_LABELS['en'];\n  return btns.map(btn => ({\n    id: btn.id,\n    title: labels[btn.id] || btn.title\n  }));\n};\n\nconst translatedButtons = translateButtons(buttons);\n\nlet payload;\nif (d.message_type === 'button') {\n  if (translatedButtons.length > 3) {\n    payload = {\n      ...base,\n      type: 'interactive',\n      interactive: {\n        type: 'list',\n        body: { text: String(d.body_text || '') },\n        action: {\n          button: 'Menu',\n          sections: sections.length ? sections : [{\n            title: 'Choose an option',\n            rows: translatedButtons.map((button) => ({\n              id: String(button.id || ''),\n              title: String(button.title || '').slice(0, 24),\n            })),\n          }],\n        },\n      },\n    };\n  } else {\n    payload = {\n      ...base,\n      type: 'interactive',\n      interactive: {\n        type: 'button',\n        body: { text: String(d.body_text || '') },\n        action: {\n          buttons: translatedButtons.map((button) => ({\n            type: 'reply',\n            reply: {\n              id: String(button.id || ''),\n              title: String(button.title || '').slice(0, 20),\n            },\n          })),\n        },\n      },\n    };\n  }\n} else if (d.message_type === 'list') {\n  payload = {\n    ...base,\n    type: 'interactive',\n    interactive: {\n      type: 'list',\n      body: { text: String(d.body_text || '') },\n      action: {\n        button: 'Menu',\n        sections,\n      },\n    },\n  };\n} else {\n  payload = {\n    ...base,\n    type: 'text',\n    text: { body: String(d.body_text || '') },\n  };\n}\n\nreturn [{ json: payload }];"},"id":"uwv2-build-payload","name":"Build Payload","type":"n8n-nodes-base.code","typeVersion":2,"position":[464,304]},{"parameters":{"method":"POST","url":"https://graph.facebook.com/v19.0/1012592638608632/messages","authentication":"predefinedCredentialType","nodeCredentialType":"whatsAppApi","sendHeaders":true,"headerParameters":{"parameters":[{"name":"Content-Type","value":"application/json"}]},"sendBody":true,"specifyBody":"json","jsonBody":"={{ JSON.stringify($json) }}","options":{}},"id":"uwv2-send-wa","name":"Send to WhatsApp","type":"n8n-nodes-base.httpRequest","typeVersion":4.4,"position":[688,304],"retryOnFail":true,"maxTries":3,"waitBetweenTries":2000,"credentials":{"whatsAppApi":{"id":"GFk530CPSyrOLT7F","name":"WhatsApp account"}},"onError":"continueRegularOutput"},{"parameters":{"jsCode":"const d = $('Start').first().json || {};\nconst payload = {\n  chat_id: String(d.chat_id || ''),\n  message_type: d.message_type || 'text',\n  body_text: String(d.body_text || ''),\n  buttons: Array.isArray(d.buttons) ? d.buttons : [],\n  list_sections: Array.isArray(d.list_sections) ? d.list_sections : [],\n  test_mode: d.test_mode === true,\n};\n\nreturn [{ json: payload }];"},"id":"uwv2-return-live","name":"Return Live Payload","type":"n8n-nodes-base.code","typeVersion":2,"position":[912,304]}],"connections":{"Start":{"main":[[{"node":"Build Payload","type":"main","index":0}]]},"Build Payload":{"main":[[{"node":"Send to WhatsApp","type":"main","index":0}]]},"Send to WhatsApp":{"main":[[{"node":"Return Live Payload","type":"main","index":0}]]}},"authors":"Vishnu Pratap","name":null,"description":null,"autosaved":false,"workflowPublishHistory":[{"createdAt":"2026-03-14T10:07:14.745Z","id":2220,"workflowId":"dO77E4A3PI9DvxVw","versionId":"bf123997-b282-4ddb-853a-fa60a70c33da","event":"deactivated","userId":"26516b95-0143-4657-99c5-c7cf19c81981"},{"createdAt":"2026-03-14T10:07:14.817Z","id":2221,"workflowId":"dO77E4A3PI9DvxVw","versionId":"bf123997-b282-4ddb-853a-fa60a70c33da","event":"activated","userId":"26516b95-0143-4657-99c5-c7cf19c81981"}]}}